moe_gen/__init__.py
moe_gen-0.0.1.dev0.dist-info/METADATA
moe_gen-0.0.1.dev0.dist-info/WHEEL
moe_gen-0.0.1.dev0.dist-info/RECORD
